other/wtm.v
module wallace_mul(input [15:0] A,input [15:0] B, output [31:0] C, input clk);

wire [15:0] A,B;
wire [31:0] C;
wire [31:0] m1,m2,m3,m4,m5,m6,m7,m8,m9,m10,m11,m12,m13,m14,m15,m16;
reg [31:0] s1,s2,s3,s4,s5,s55,s6,s7,s8,s9,s10,s11,s12,s13,s14,m161,m162,m163;
reg [31:0] c1,c2,c3,c4,c5,c6,c7,c8,c9,c10,c11,c12,c13,c14,c51,c52,c131;
wire [31:0] s15,c15;

assign m1 = B[0]?{16'b0,A}:32'b0;
assign m2 = B[1]?{15'b0,A,1'b0}:32'b0;
assign m3 = B[2]?{14'b0,A,2'b0}:32'b0;
assign m4 = B[3]?{13'b0,A,3'b0}:32'b0;
assign m5 = B[4]?{12'b0,A,4'b0}:32'b0;
assign m6 = B[5]?{11'b0,A,5'b0}:32'b0;
assign m7 = B[6]?{10'b0,A,6'b0}:32'b0;
assign m8 = B[7]?{9'b0,A,7'b0}:32'b0;
assign m9 = B[8]?{8'b0,A,8'b0}:32'b0;
assign m10 = B[9]?{7'b0,A,9'b0}:32'b0;
assign m11 = B[10]?{6'b0,A,10'b0}:32'b0;
assign m12 = B[11]?{5'b0,A,11'b0}:32'b0;
assign m13 = B[12]?{4'b0,A,12'b0}:32'b0;
assign m14 = B[13]?{3'b0,A,13'b0}:32'b0;
assign m15 = B[14]?{2'b0,A,14'b0}:32'b0;
assign m16 = B[15]?{1'b0,A,15'b0}:32'b0;

always @(posedge clk) begin
s1<=m1^m2^m3;
c1<={((m1&m2)+(m3&(m1^m2))),1'b0};

s2<=m6^m4^m5;
c2<={((m6&m4)+(m5&(m6^m4))),1'b0};

s3<=m7^m8^m9;
c3<={((m8&m7)+(m9&(m7^m8))),1'b0};

s4<=m10^m11^m12;
c4<={((m10&m11)+(m12&(m10^m11))),1'b0};

s5<=m13^m14^m15;
c5<={((m13&m14)+(m15&(m13^m14))),1'b0};

m161<=m16;
/*****************LEVEL1***********************/

s6<=s2^s1^c1;
c6<={((s1&c1)+(s2&(s1^c1))),1'b0};

s7<=c3^c2^s3;
c7<={((c3&c2)+(s3&(c3^c2))),1'b0};

s8<=s5^c4^s4;
c8<={((s5&c4)+(s4&(s5^c4))),1'b0};

c51<=c5;
m162<=m161;
/*****************LEVEL2**********************/

s10<=c6^s6^s7;
c10<={((c6&s6)+(s7&(c6^s6))),1'b0};

s11<=s8^c8^c7;
c11<={((s8&c8)+(c7&(s8^c8))),1'b0};

c52<=c51;
m163<=m162;
/****************LEVEL3************************/

s12<=s10^c10^s11;
c12<={((s10&c10)+(s11&(s10^c10))),1'b0};

s13<=c11^m163^c52;
c13<={((c11&m163)+(c52&(c11^m163))),1'b0};
/*****************LEVEL4**********************/

s14<=c12^s12^s13;
c14<={((c12&s12)+(s13&(c12^s12))),1'b0};

c131<=c13;
/****************LEVEL4**********************/
end
assign s15=s14^c14^c131;
assign c15={((c14&s14)+(c131&(s14^c14))),1'b0};

//CarryLookAhead Adder Ahead:
reg [31:0] g1,g2,g3,g4,g5,p1,p2,p3,p4,XorOut1,XorOut2,XorOut3,XorOut4,XorOut5;  //P for XOR And G for AND

    reg [32:0] G,P; //C for Output
    always @(posedge clk) begin
    P<={s15^c15,1'b0};
    G<={s15&c15,1'b0};
    end
    genvar i;
    generate
    for(i=1;i<32;i=i+1) begin:FirstStage //s=naya g+ naya p*purana g
        always @(posedge clk) begin
        g1[i]<=(G[i-1]&P[i])+G[i];
        p1[i]<=P[i]&P[i-1];

        XorOut1<=P[32:1];
        end
    end
    for(i=2;i<32;i=i+1) begin:SecondStage //s=naya g+ naya p*purana g
        always @(posedge clk) begin
        g2[i]<=(g1[i-2]&p1[i])+g1[i];
        p2[i]<=p1[i]&p1[i-2];

        XorOut2<=XorOut1;
        end
    end
    for(i=4;i<32;i=i+1) begin:ThirdStage //s=naya g+ naya p*purana g
        always @(posedge clk) begin
        g3[i]<=(g2[i-4]&p2[i])+g2[i];
        p3[i]<=p2[i]&p2[i-4];

        XorOut3<=XorOut2;
        end
    end
    for(i=8;i<32;i=i+1) begin:FourthStage //s=naya g+ naya p*purana g
        always @(posedge clk) begin
        g4[i]<=(g3[i-8]&p3[i])+g3[i];
        p4[i]<=p3[i]&p3[i-8];

        XorOut4<=XorOut3;
        end
    end
    for(i=16;i<32;i=i+1) begin:FifthStage
    	always @(posedge clk) begin
        g5[i]<=(g4[i-16]&p4[i])+g4[i];

        XorOut5<=XorOut4;
        end
    end
    always@(posedge clk) begin
    g1[0]<=G[0];

    g2[0]<=g1[0];
    g2[1]<=g1[1];
    end

    for(i=0;i<4;i=i+1)
        always @(posedge clk) g3[i]<=g2[i];

    for(i=0;i<8;i=i+1)
        always @(posedge clk) g4[i]<=g3[i];

    for(i=0;i<16;i=i+1)
    	always @(posedge clk) g5[i]<=g4[i];

    endgenerate

    assign C=XorOut5^g5;


endmodule

other/wtm_tb.v
module mul_tb();

    reg [15:0] InputA, InputB;
    wire [31:0] Output;
    reg Clock;
    wallace_mul obj (
          .A(InputA),
          .B(InputB),
          .C(Output),
          .clk(Clock)
    );
    initial begin
            $dumpfile("wtm.vcd");
            $dumpvars(0,mul_tb);
    Clock<=1'b0;
    InputA<=12;
    InputB<=3;
    #2;
    InputA<=34;
    InputB<=11;
    #2;
    InputA<=34;
    InputB<=11;
    #1000;
    $finish;
    end
    always@(InputA|Output)
        $display($time,"%d   %d  =  %d    %b",InputA,InputB,Output,Clock);

    always begin
    #1 Clock <= !Clock;
    end

endmodule

other/wtm.vcd
$date
	Fri Mar  8 13:34:02 2019
$end
$version
	Icarus Verilog
$end
$timescale
	1s
$end
$scope module mul_tb $end
$var wire 32 ! Output [31:0] $end
$var reg 1 " Clock $end
$var reg 16 # InputA [15:0] $end
$var reg 16 $ InputB [15:0] $end
$scope module obj $end
$var wire 16 % A [15:0] $end
$var wire 16 & B [15:0] $end
$var wire 32 ' C [31:0] $end
$var wire 1 " clk $end
$var wire 32 ( s15 [31:0] $end
$var wire 32 ) m9 [31:0] $end
$var wire 32 * m8 [31:0] $end
$var wire 32 + m7 [31:0] $end
$var wire 32 , m6 [31:0] $end
$var wire 32 - m5 [31:0] $end
$var wire 32 . m4 [31:0] $end
$var wire 32 / m3 [31:0] $end
$var wire 32 0 m2 [31:0] $end
$var wire 32 1 m16 [31:0] $end
$var wire 32 2 m15 [31:0] $end
$var wire 32 3 m14 [31:0] $end
$var wire 32 4 m13 [31:0] $end
$var wire 32 5 m12 [31:0] $end
$var wire 32 6 m11 [31:0] $end
$var wire 32 7 m10 [31:0] $end
$var wire 32 8 m1 [31:0] $end
$var wire 32 9 c15 [31:0] $end
$var reg 33 : G [32:0] $end
$var reg 33 ; P [32:0] $end
$var reg 32 < XorOut1 [31:0] $end
$var reg 32 = XorOut2 [31:0] $end
$var reg 32 > XorOut3 [31:0] $end
$var reg 32 ? XorOut4 [31:0] $end
$var reg 32 @ XorOut5 [31:0] $end
$var reg 32 A c1 [31:0] $end
$var reg 32 B c10 [31:0] $end
$var reg 32 C c11 [31:0] $end
$var reg 32 D c12 [31:0] $end
$var reg 32 E c13 [31:0] $end
$var reg 32 F c131 [31:0] $end
$var reg 32 G c14 [31:0] $end
$var reg 32 H c2 [31:0] $end
$var reg 32 I c3 [31:0] $end
$var reg 32 J c4 [31:0] $end
$var reg 32 K c5 [31:0] $end
$var reg 32 L c51 [31:0] $end
$var reg 32 M c52 [31:0] $end
$var reg 32 N c6 [31:0] $end
$var reg 32 O c7 [31:0] $end
$var reg 32 P c8 [31:0] $end
$var reg 32 Q g1 [31:0] $end
$var reg 32 R g2 [31:0] $end
$var reg 32 S g3 [31:0] $end
$var reg 32 T g4 [31:0] $end
$var reg 32 U g5 [31:0] $end
$var reg 32 V m161 [31:0] $end
$var reg 32 W m162 [31:0] $end
$var reg 32 X m163 [31:0] $end
$var reg 32 Y p1 [31:0] $end
$var reg 32 Z p2 [31:0] $end
$var reg 32 [ p3 [31:0] $end
$var reg 32 \ p4 [31:0] $end
$var reg 32 ] s1 [31:0] $end
$var reg 32 ^ s10 [31:0] $end
$var reg 32 _ s11 [31:0] $end
$var reg 32 ` s12 [31:0] $end
$var reg 32 a s13 [31:0] $end
$var reg 32 b s14 [31:0] $end
$var reg 32 c s2 [31:0] $end
$var reg 32 d s3 [31:0] $end
$var reg 32 e s4 [31:0] $end
$var reg 32 f s5 [31:0] $end
$var reg 32 g s6 [31:0] $end
$var reg 32 h s7 [31:0] $end
$var reg 32 i s8 [31:0] $end
$scope begin FifthStage[16] $end
$upscope $end
$scope begin FifthStage[17] $end
$upscope $end
$scope begin FifthStage[18] $end
$upscope $end
$scope begin FifthStage[19] $end
$upscope $end
$scope begin FifthStage[20] $end
$upscope $end
$scope begin FifthStage[21] $end
$upscope $end
$scope begin FifthStage[22] $end
$upscope $end
$scope begin FifthStage[23] $end
$upscope $end
$scope begin FifthStage[24] $end
$upscope $end
$scope begin FifthStage[25] $end
$upscope $end
$scope begin FifthStage[26] $end
$upscope $end
$scope begin FifthStage[27] $end
$upscope $end
$scope begin FifthStage[28] $end
$upscope $end
$scope begin FifthStage[29] $end
$upscope $end
$scope begin FifthStage[30] $end
$upscope $end
$scope begin FifthStage[31] $end
$upscope $end
$scope begin FirstStage[1] $end
$upscope $end
$scope begin FirstStage[2] $end
$upscope $end
$scope begin FirstStage[3] $end
$upscope $end
$scope begin FirstStage[4] $end
$upscope $end
$scope begin FirstStage[5] $end
$upscope $end
$scope begin FirstStage[6] $end
$upscope $end
$scope begin FirstStage[7] $end
$upscope $end
$scope begin FirstStage[8] $end
$upscope $end
$scope begin FirstStage[9] $end
$upscope $end
$scope begin FirstStage[10] $end
$upscope $end
$scope begin FirstStage[11] $end
$upscope $end
$scope begin FirstStage[12] $end
$upscope $end
$scope begin FirstStage[13] $end
$upscope $end
$scope begin FirstStage[14] $end
$upscope $end
$scope begin FirstStage[15] $end
$upscope $end
$scope begin FirstStage[16] $end
$upscope $end
$scope begin FirstStage[17] $end
$upscope $end
$scope begin FirstStage[18] $end
$upscope $end
$scope begin FirstStage[19] $end
$upscope $end
$scope begin FirstStage[20] $end
$upscope $end
$scope begin FirstStage[21] $end
$upscope $end
$scope begin FirstStage[22] $end
$upscope $end
$scope begin FirstStage[23] $end
$upscope $end
$scope begin FirstStage[24] $end
$upscope $end
$scope begin FirstStage[25] $end
$upscope $end
$scope begin FirstStage[26] $end
$upscope $end
$scope begin FirstStage[27] $end
$upscope $end
$scope begin FirstStage[28] $end
$upscope $end
$scope begin FirstStage[29] $end
$upscope $end
$scope begin FirstStage[30] $end
$upscope $end
$scope begin FirstStage[31] $end
$upscope $end
$scope begin FourthStage[8] $end
$upscope $end
$scope begin FourthStage[9] $end
$upscope $end
$scope begin FourthStage[10] $end
$upscope $end
$scope begin FourthStage[11] $end
$upscope $end
$scope begin FourthStage[12] $end
$upscope $end
$scope begin FourthStage[13] $end
$upscope $end
$scope begin FourthStage[14] $end
$upscope $end
$scope begin FourthStage[15] $end
$upscope $end
$scope begin FourthStage[16] $end
$upscope $end
$scope begin FourthStage[17] $end
$upscope $end
$scope begin FourthStage[18] $end
$upscope $end
$scope begin FourthStage[19] $end
$upscope $end
$scope begin FourthStage[20] $end
$upscope $end
$scope begin FourthStage[21] $end
$upscope $end
$scope begin FourthStage[22] $end
$upscope $end
$scope begin FourthStage[23] $end
$upscope $end
$scope begin FourthStage[24] $end
$upscope $end
$scope begin FourthStage[25] $end
$upscope $end
$scope begin FourthStage[26] $end
$upscope $end
$scope begin FourthStage[27] $end
$upscope $end
$scope begin FourthStage[28] $end
$upscope $end
$scope begin FourthStage[29] $end
$upscope $end
$scope begin FourthStage[30] $end
$upscope $end
$scope begin FourthStage[31] $end
$upscope $end
$scope begin SecondStage[2] $end
$upscope $end
$scope begin SecondStage[3] $end
$upscope $end
$scope begin SecondStage[4] $end
$upscope $end
$scope begin SecondStage[5] $end
$upscope $end
$scope begin SecondStage[6] $end
$upscope $end
$scope begin SecondStage[7] $end
$upscope $end
$scope begin SecondStage[8] $end
$upscope $end
$scope begin SecondStage[9] $end
$upscope $end
$scope begin SecondStage[10] $end
$upscope $end
$scope begin SecondStage[11] $end
$upscope $end
$scope begin SecondStage[12] $end
$upscope $end
$scope begin SecondStage[13] $end
$upscope $end
$scope begin SecondStage[14] $end
$upscope $end
$scope begin SecondStage[15] $end
$upscope $end
$scope begin SecondStage[16] $end
$upscope $end
$scope begin SecondStage[17] $end
$upscope $end
$scope begin SecondStage[18] $end
$upscope $end
$scope begin SecondStage[19] $end
$upscope $end
$scope begin SecondStage[20] $end
$upscope $end
$scope begin SecondStage[21] $end
$upscope $end
$scope begin SecondStage[22] $end
$upscope $end
$scope begin SecondStage[23] $end
$upscope $end
$scope begin SecondStage[24] $end
$upscope $end
$scope begin SecondStage[25] $end
$upscope $end
$scope begin SecondStage[26] $end
$upscope $end
$scope begin SecondStage[27] $end
$upscope $end
$scope begin SecondStage[28] $end
$upscope $end
$scope begin SecondStage[29] $end
$upscope $end
$scope begin SecondStage[30] $end
$upscope $end
$scope begin SecondStage[31] $end
$upscope $end
$scope begin ThirdStage[4] $end
$upscope $end
$scope begin ThirdStage[5] $end
$upscope $end
$scope begin ThirdStage[6] $end
$upscope $end
$scope begin ThirdStage[7] $end
$upscope $end
$scope begin ThirdStage[8] $end
$upscope $end
$scope begin ThirdStage[9] $end
$upscope $end
$scope begin ThirdStage[10] $end
$upscope $end
$scope begin ThirdStage[11] $end
$upscope $end
$scope begin ThirdStage[12] $end
$upscope $end
$scope begin ThirdStage[13] $end
$upscope $end
$scope begin ThirdStage[14] $end
$upscope $end
$scope begin ThirdStage[15] $end
$upscope $end
$scope begin ThirdStage[16] $end
$upscope $end
$scope begin ThirdStage[17] $end
$upscope $end
$scope begin ThirdStage[18] $end
$upscope $end
$scope begin ThirdStage[19] $end
$upscope $end
$scope begin ThirdStage[20] $end
$upscope $end
$scope begin ThirdStage[21] $end
$upscope $end
$scope begin ThirdStage[22] $end
$upscope $end
$scope begin ThirdStage[23] $end
$upscope $end
$scope begin ThirdStage[24] $end
$upscope $end
$scope begin ThirdStage[25] $end
$upscope $end
$scope begin ThirdStage[26] $end
$upscope $end
$scope begin ThirdStage[27] $end
$upscope $end
$scope begin ThirdStage[28] $end
$upscope $end
$scope begin ThirdStage[29] $end
$upscope $end
$scope begin ThirdStage[30] $end
$upscope $end
$scope begin ThirdStage[31] $end
$upscope $end
$scope begin genblk6[0] $end
$upscope $end
$scope begin genblk6[1] $end
$upscope $end
$scope begin genblk6[2] $end
$upscope $end
$scope begin genblk6[3] $end
$upscope $end
$scope begin genblk7[0] $end
$upscope $end
$scope begin genblk7[1] $end
$upscope $end
$scope begin genblk7[2] $end
$upscope $end
$scope begin genblk7[3] $end
$upscope $end
$scope begin genblk7[4] $end
$upscope $end
$scope begin genblk7[5] $end
$upscope $end
$scope begin genblk7[6] $end
$upscope $end
$scope begin genblk7[7] $end
$upscope $end
$scope begin genblk8[0] $end
$upscope $end
$scope begin genblk8[1] $end
$upscope $end
$scope begin genblk8[2] $end
$upscope $end
$scope begin genblk8[3] $end
$upscope $end
$scope begin genblk8[4] $end
$upscope $end
$scope begin genblk8[5] $end
$upscope $end
$scope begin genblk8[6] $end
$upscope $end
$scope begin genblk8[7] $end
$upscope $end
$scope begin genblk8[8] $end
$upscope $end
$scope begin genblk8[9] $end
$upscope $end
$scope begin genblk8[10] $end
$upscope $end
$scope begin genblk8[11] $end
$upscope $end
$scope begin genblk8[12] $end
$upscope $end
$scope begin genblk8[13] $end
$upscope $end
$scope begin genblk8[14] $end
$upscope $end
$scope begin genblk8[15] $end
$upscope $end
$upscope $end
$upscope $end
$enddefinitions $end
#0
$dumpvars
bx i
bx h
bx g
bx f
bx e
bx d
bx c
bx b
bx a
bx `
bx _
bx ^
bx ]
bx \
bx [
bx Z
bx Y
bx X
bx W
bx V
bx U
bx T
bx S
bx R
bx Q
bx P
bx O
bx N
bx M
bx L
bx K
bx J
bx I
bx H
bx G
bx F
bx E
bx D
bx C
bx B
bx A
bx @
bx ?
bx >
bx =
bx <
bx ;
bx :
bx0 9
b1100 8
b0 7
b0 6
b0 5
b0 4
b0 3
b0 2
b0 1
b11000 0
b0 /
b0 .
b0 -
b0 ,
b0 +
b0 *
b0 )
bx (
bx '
b11 &
b1100 %
b11 $
b1100 #
0"
bx !
$end
#1
bx0 G
bx0 E
bx0 D
bx0 C
bx0 B
bx0 P
bx0 O
bx0 N
b0 V
b0 K
b0 f
b0 J
b0 e
b0 I
b0 d
b0 H
b0 c
b10000 A
b10100 ]
bx00 :
bx0 ;
1"
#2
b100010000 .
b100010 8
b1000100 0
0"
b1011 $
b1011 &
b100010 #
b100010 %
#3
bx0 F
b0 W
b0 L
b0 P
b0 i
b0 O
b0 h
b100000 N
b100 g
b100010000 c
b0 A
b1100110 ]
bx0x Y
bx00 Q
1"
#4
0"
#5
bx0xxx Z
b0 X
b0 M
b0 C
b0 _
b0 B
b100100 ^
b0 N
b101110110 g
bx00 R
1"
#6
0"
#7
b0 E
b0 a
b0 D
b100100 `
b101110110 ^
bx00 S
bx0xxxxxxx [
1"
#8
0"
#9
b0 9
b100100 (
bx0xxxxxxxxxxxxxxx \
bx00 T
b0 F
b0 G
b100100 b
b101110110 `
1"
#10
0"
#11
b101110110 (
b0 :
b1001000 ;
b101110110 b
bx00 U
1"
#12
0"
#13
b100100 <
b0x Y
b0 Q
b1011101100 ;
1"
#14
0"
#15
b100100 =
b0xx Z
b0 R
b1100100x Y
b101110110 <
1"
#16
0"
#17
b101110110 =
b100100 >
b0xxxx [
b0 S
1"
#18
0"
#19
b100100 ?
b0xxxxxxxx \
b0 T
b101110110 >
1"
#20
0"
#21
b100100 !
b100100 '
b101110110 ?
b100100 @
b0 U
1"
#22
0"
#23
b101110110 !
b101110110 '
b101110110 @
1"
