Cache/new/cache.v
module cache(read1,write1,writedata,readHit,r1e,w1e,clk,readout1);
input [15:0]write1;
input [15:0]writedata;
input r1e,w1e,clk;
input [15:0]read1;
output [15:0]readout1;
output readHit;
reg[15:0]readout1;
reg [262:0]cache[127:0];
reg [15:0]mem[65535:0];
reg [4:0]tag;
reg [6:0]index;
reg [15:0]mem_ind,mem_ind1;
reg [7:0]rem;
reg readHit;
integer t;
initial begin
  for(t=0;t<128;t=t+1) begin
    cache[t]<=0;
  end
  for(t=0;t<65535;t=t+1)begin
    mem[t]<=0;
  end
  mem[0]<=1500;
  mem[1]<=1020;
  mem[16]<=156;
  mem[128]<=32;
end
integer i;
integer j;
always @ (posedge clk) begin
    tag=read1[15:11];
    index=read1[10:4];
    rem=read1[3:0]<<4;
    mem_ind={read1[15:4],{4'b0000}};
    mem_ind1=mem_ind;
      if(r1e==1) begin                                     //valid bit
        if(read1[tag]==cache[index][262:258] && cache[index][257]==1) begin    //read hit
            readHit=1;
            readout1=cache[index][rem+15-:15];
        end
      else begin
            readHit=0;
            // $display("read miss");                //dirtybit
            if(cache[index][257]==0 || cache[index][256]==0) begin
              j=15;
              for(i=0;i<16;i=i+1) begin
                cache[index][j-:15]=mem[mem_ind];
              //  $display("%b",cache[index][j-:15]);
                mem_ind=mem_ind+1;
                j=j+16;
              end
              cache[index][257]=1;
              readout1=cache[index][rem+15-:15];
            end
            else begin
              if(cache[index][256]==1) begin   //dirtybit=1
                  j=15;
                  for(i=0;i<16;i=i+1) begin
                    mem[mem_ind1]=cache[index][j-:15];
                    mem_ind1=mem_ind1+1;
                    j=j+16;
                  end
                  j=15;
                  for(i=0;i<16;i=i+1) begin
                    cache[index][j-:15]=mem[mem_ind];
                    mem_ind=mem_ind+1;
                    j=j+16;
                  end
                  cache[index][257]=1;
                  readout1=cache[index][rem+15-:15];
              end
            end
      end
    end



    if(w1e==1) begin
        if(write1[tag]==cache[index][262:258] && cache[index][257]==1) begin
          cache[index][rem+15-:15]=writedata;
          cache[index][256]=1;
        end
      else begin
          if(cache[index][257]==0 || cache[index][256]==0) begin
            j=15;
            for(i=0;i<16;i=i+1) begin
              cache[index][j-:15]=mem[mem_ind];
              mem_ind=mem_ind+1;
              j=j+16;
            end
            cache[index][257]=1;
            cache[index][rem+15-:15]=writedata;
            cache[index][256]=1;
          end
          else begin
            if(cache[index][256]==1) begin
                j=15;
                for(i=0;i<16;i=i+1) begin
                  mem[mem_ind1]=cache[index][j-:15];
                  mem_ind1=mem_ind1+1;
                  j=j+16;
                end
                j=15;
                for(i=0;i<16;i=i+1) begin
                  cache[index][j-:15]=mem[mem_ind];
                  mem_ind=mem_ind+1;
                  j=j+16;
                end
                cache[index][257]=1;
                cache[index][rem+15-:15]=writedata;
                cache[index][256]=1;
            end
          end
      end
    end
end
endmodule

Cache/new/cachetb.v
module cachetb;
reg clk;
reg [15:0]write1,read1,writedata;
reg r1e,w1e;
wire readHit;
wire [15:0]readout1;
always
  #1 clk=!clk;
cache obj(
  .read1(read1),
  .write1(write1),
  .writedata(writedata),
  .r1e(r1e),
  .w1e(w1e),
  .clk(clk),
  .readHit(readHit),
  .readout1(readout1)
  );
initial begin
  clk=0;
  r1e=1;read1=0;
  #4;
  r1e=1;read1=1;
  #4;
  r1e=0;w1e=1;
  write1=1;writedata=343;
  #4;
  w1e=0;r1e=1;
  #4;
  read1=16;
  #4;
  read1=128;
  #4;
  read1=1;
  #20 $finish;
end

initial begin
  $dumpfile("cachetb.vcd");
  $dumpvars(0,cachetb);
  $monitor(" %d  %d  %d",read1,readout1,readHit);
end



endmodule

Cache/new/cachetb.vcd
$date
	Sat Apr 27 19:28:49 2019
$end
$version
	Icarus Verilog
$end
$timescale
	1s
$end
$scope module cachetb $end
$var wire 16 ! readout1 [15:0] $end
$var wire 1 " readHit $end
$var reg 1 # clk $end
$var reg 1 $ r1e $end
$var reg 16 % read1 [15:0] $end
$var reg 1 & w1e $end
$var reg 16 ' write1 [15:0] $end
$var reg 16 ( writedata [15:0] $end
$scope module obj $end
$var wire 1 # clk $end
$var wire 1 $ r1e $end
$var wire 16 ) read1 [15:0] $end
$var wire 1 & w1e $end
$var wire 16 * write1 [15:0] $end
$var wire 16 + writedata [15:0] $end
$var reg 7 , index [6:0] $end
$var reg 16 - mem_ind [15:0] $end
$var reg 16 . mem_ind1 [15:0] $end
$var reg 1 " readHit $end
$var reg 16 / readout1 [15:0] $end
$var reg 8 0 rem [7:0] $end
$var reg 5 1 tag [4:0] $end
$var integer 32 2 i [31:0] $end
$var integer 32 3 j [31:0] $end
$var integer 32 4 t [31:0] $end
$upscope $end
$upscope $end
$enddefinitions $end
#0
$dumpvars
b1111111111111111 4
bx 3
bx 2
bx 1
bx 0
bx /
bx .
bx -
bx ,
bx +
bx *
b0 )
bx (
bx '
x&
b0 %
1$
0#
x"
bx !
$end
#1
b10111011100 !
b10111011100 /
b10000 2
b100001111 3
0"
b0 .
b10000 -
b0 0
b0 ,
b0 1
1#
#2
0#
#3
1"
b0 -
1#
#4
0#
b1 %
b1 )
#5
b1111111100 !
b1111111100 /
b10000 -
b10000 2
b100001111 3
0"
b10000 0
1#
#6
0#
#7
b10000 2
b100001111 3
b10000 -
1#
#8
0#
b101010111 (
b101010111 +
b1 '
b1 *
1&
0$
#9
b10000 2
b100001111 3
b10000 -
1#
#10
0#
#11
b10000 .
b10000 2
b100001111 3
b10000 -
1#
#12
0#
1$
0&
#13
b101010111 !
b101010111 /
b10000 2
b100001111 3
b10000 .
b10000 -
1#
#14
0#
#15
b10000 2
b100001111 3
b10000 .
b10000 -
1#
#16
0#
b10000 %
b10000 )
#17
b10011100 !
b10011100 /
b100000 -
b10000 2
b100001111 3
b0 0
b1 ,
1#
#18
0#
#19
1"
b10000 -
1#
#20
0#
b10000000 %
b10000000 )
#21
b100000 !
b100000 /
b10000 2
b100001111 3
0"
b10000000 .
b10010000 -
b1000 ,
1#
#22
0#
#23
1"
b10000000 -
1#
#24
0#
b1 %
b1 )
#25
b101010111 !
b101010111 /
b10000 2
b100001111 3
0"
b10000 .
b10000 -
b10000 0
b0 ,
1#
#26
0#
#27
b10000 2
b100001111 3
b10000 .
b10000 -
1#
#28
0#
#29
b10000 2
b100001111 3
b10000 .
b10000 -
1#
#30
0#
#31
b10000 2
b100001111 3
b10000 .
b10000 -
1#
#32
0#
#33
b10000 2
b100001111 3
b10000 .
b10000 -
1#
#34
0#
#35
b10000 2
b100001111 3
b10000 .
b10000 -
1#
#36
0#
#37
b10000 2
b100001111 3
b10000 .
b10000 -
1#
#38
0#
#39
b10000 2
b100001111 3
b10000 .
b10000 -
1#
#40
0#
#41
b10000 2
b100001111 3
b10000 .
b10000 -
1#
#42
0#
#43
b10000 2
b100001111 3
b10000 .
b10000 -
1#
